Metadata-Version: 2.1
Name: 7uring
Version: 1.0.0
Summary: An advanced cryptography tool.
Home-page: https://github.com/karthikuj/7uring
Author: Karthik UJ
Author-email: karthikuj2001@gmail.com
License: UNKNOWN
Download-URL: https://github.com/karthikuj/7uring/archive/refs/tags/v1.0.tar.gz
Project-URL: Bug Tracker, https://github.com/karthikuj/7uring/issues
Keywords: hashing,encoding,encryption,steganography,cryptanalysis,steganalysis,cipher
Platform: UNKNOWN
Classifier: Programming Language :: Python :: 3
Classifier: License :: OSI Approved :: GNU General Public License v3 (GPLv3)
Classifier: Operating System :: OS Independent
Requires-Python: >=3.6
